{
  "agent_contract": "docs/ail/corpus/e2e/agents/codex-ail-spec-writer.md",
  "agent_contract_version": "0.1.0",
  "codex_model": "codex-subagent-default",
  "executor_label": "codex-ail-spec-writer",
  "input": {
    "package_manifest_file": "examples/ail_std_collections.ail/ail-package.md",
    "required_features": [
      "stdlib",
      "types",
      "functions",
      "collection-transform",
      "traces"
    ],
    "requirements_source": "inline checked requirements from active AIL v0.2 e2e capture session"
  },
  "package": "examples/ail_std_collections.ail",
  "profile": "Application",
  "prompt_file": "docs/ail/prompts/core-draft.system.md",
  "prompt_version": "ail-prompts.v0.2",
  "task": "Draft complete canonical AIL-Spec text for the AIL Standard Collections package from checked requirements."
}
